sqlcrud/__init__.py
sqlcrud/crud.py
sqlcrud-1.0.0.dist-info/LICENSE
sqlcrud-1.0.0.dist-info/METADATA
sqlcrud-1.0.0.dist-info/WHEEL
sqlcrud-1.0.0.dist-info/top_level.txt
sqlcrud-1.0.0.dist-info/RECORD
