Metadata-Version: 2.1
Name: sqlcrud
Version: 1.0.0
Summary: Simple crud operator on top sqlmodel
Home-page: https://github.com/johanalmquist/sqlcrud
Author: Johan Almquist
Author-email: hello@johanalmquist.se
License: UNKNOWN
Platform: UNKNOWN
Classifier: Programming Language :: Python :: 3
Classifier: License :: OSI Approved :: MIT License
Classifier: Operating System :: OS Independent
Requires-Python: >=3.8
License-File: LICENSE
Requires-Dist: sqlmodel (==0.0.6)
